{
	"credit": "LeonidM",
	"textures": {
		"0": "numbers:item/number/0",
		"particle": "numbers:item/number/0"
	},
	"elements": [
		{
			"from": [11.5, 0, 0],
			"to": [19.5, 8, 1],
			"faces": {
				"north": {"uv": [0, 0, 16, 16], "texture": "#0"},
				"east": {"uv": [0, 0, 1, 1], "texture": "#0"},
				"south": {"uv": [0, 0, 16, 16], "texture": "#0"},
				"west": {"uv": [0, 0, 1, 1], "texture": "#0"},
				"up": {"uv": [0, 0, 1, 1], "texture": "#0"},
				"down": {"uv": [0, 0, 1, 1], "texture": "#0"}
			}
		}
	],
	"display": {
		"fixed": {
			"translation": [0, 10.375, 7.75],
			"scale": [0.5, 0.5, 1]
		}
	}
}